pinax/__init__.py
pinax/images/__init__.py
pinax/images/admin.py
pinax/images/apps.py
pinax/images/compat.py
pinax/images/models.py
pinax/images/specs.py
pinax/images/urls.py
pinax/images/utils.py
pinax/images/views.py
pinax/images/migrations/0001_initial.py
pinax/images/migrations/__init__.py
pinax/images/tests/__init__.py
pinax/images/tests/test.py
pinax/images/tests/tests.py
pinax/images/tests/urls.py
pinax_images-5.0.1.dist-info/AUTHORS
pinax_images-5.0.1.dist-info/LICENSE
pinax_images-5.0.1.dist-info/METADATA
pinax_images-5.0.1.dist-info/WHEEL
pinax_images-5.0.1.dist-info/top_level.txt
pinax_images-5.0.1.dist-info/RECORD
