Metadata-Version: 2.1
Name: pinax-images
Version: 5.0.1
Summary: an app for managing collections of images associated with a content object
Home-page: https://github.com/pinax/pinax-images/
Author: Pinax Team
Author-email: team@pinaxproject.com
License: MIT
Platform: UNKNOWN
Classifier: Development Status :: 5 - Production/Stable
Classifier: Environment :: Web Environment
Classifier: Framework :: Django
Classifier: Framework :: Django :: 2.2
Classifier: Framework :: Django :: 3.2
Classifier: Intended Audience :: Developers
Classifier: License :: OSI Approved :: MIT License
Classifier: Operating System :: OS Independent
Classifier: Programming Language :: Python
Classifier: Programming Language :: Python :: 3
Classifier: Programming Language :: Python :: 3.6
Classifier: Programming Language :: Python :: 3.7
Classifier: Programming Language :: Python :: 3.8
Classifier: Programming Language :: Python :: 3.9
Classifier: Programming Language :: Python :: 3.10
Classifier: Topic :: Software Development :: Libraries :: Python Modules
License-File: LICENSE
License-File: AUTHORS
Requires-Dist: django (>=2.2)
Requires-Dist: django-imagekit (>=4.0.2)
Requires-Dist: pilkit (>=2.0.0)
Requires-Dist: pillow (>=7.1.2)
Requires-Dist: pytz (>=2020.1)
